{
  "TEST": {
    "last_updated": "2026-02-14T18:44:42.761347Z",
    "last_fetch_status": "success",
    "data_points": 1
  },
  "NVDA": {
    "last_updated": "2026-03-12T10:08:53.904606Z",
    "last_fetch_status": "success",
    "data_points": 117
  },
  "AMD": {
    "last_updated": "2026-03-12T10:08:55.116456Z",
    "last_fetch_status": "success",
    "data_points": 117
  },
  "INTC": {
    "last_updated": "2026-03-12T10:08:56.442545Z",
    "last_fetch_status": "success",
    "data_points": 117
  },
  "SOXX": {
    "last_updated": "2026-03-12T11:08:06.501929Z",
    "last_fetch_status": "success",
    "data_points": 117
  },
  "MSFT": {
    "last_updated": "2026-03-12T11:08:07.694907Z",
    "last_fetch_status": "success",
    "data_points": 117
  },
  "GOOGL": {
    "last_updated": "2026-03-12T11:08:08.832872Z",
    "last_fetch_status": "success",
    "data_points": 117
  },
  "AMZN": {
    "last_updated": "2026-03-12T10:08:48.330466Z",
    "last_fetch_status": "success",
    "data_points": 117
  },
  "META": {
    "last_updated": "2026-03-12T10:08:50.459735Z",
    "last_fetch_status": "success",
    "data_points": 117
  },
  "SPY": {
    "last_updated": "2026-03-12T10:08:51.688213Z",
    "last_fetch_status": "success",
    "data_points": 117
  },
  "QQQ": {
    "last_updated": "2026-03-12T10:08:52.810148Z",
    "last_fetch_status": "success",
    "data_points": 117
  },
  "VIX": {
    "last_updated": "2026-02-14T20:35:29.964419Z",
    "last_fetch_status": "failed: API Error: Invalid API call. Please retry or visit the documentation (https://www.alphavantage.co/documentation/) for TIME_SERIES_DAILY.",
    "data_points": 0
  },
  "BTC-USD": {
    "last_updated": "2026-03-12T10:08:45.916702Z",
    "last_fetch_status": "success",
    "data_points": 118
  },
  "ETH-USD": {
    "last_updated": "2026-03-12T09:11:10.418362Z",
    "last_fetch_status": "success",
    "data_points": 118
  },
  "^VIX": {
    "last_updated": "2026-03-12T10:08:49.389714Z",
    "last_fetch_status": "success",
    "data_points": 81
  },
  "NQ=F": {
    "last_updated": "2026-03-12T11:08:09.964221Z",
    "last_fetch_status": "success",
    "data_points": 85
  },
  "AVGO": {
    "last_updated": "2026-03-12T10:08:47.218159Z",
    "last_fetch_status": "success",
    "data_points": 79
  },
  "ASML": {
    "last_updated": "2026-03-12T11:08:11.142105Z",
    "last_fetch_status": "success",
    "data_points": 79
  },
  "LRCX": {
    "last_updated": "2026-03-12T11:08:12.302728Z",
    "last_fetch_status": "success",
    "data_points": 79
  },
  "MU": {
    "last_updated": "2026-03-12T11:08:13.521366Z",
    "last_fetch_status": "success",
    "data_points": 79
  },
  "TSM": {
    "last_updated": "2026-03-12T11:08:14.773166Z",
    "last_fetch_status": "success",
    "data_points": 79
  },
  "PLTR": {
    "last_updated": "2026-03-12T11:08:15.901412Z",
    "last_fetch_status": "success",
    "data_points": 79
  },
  "CRWD": {
    "last_updated": "2026-03-12T11:08:17.036905Z",
    "last_fetch_status": "success",
    "data_points": 79
  },
  "NFLX": {
    "last_updated": "2026-03-12T11:51:55.658552Z",
    "last_fetch_status": "success",
    "data_points": 79
  },
  "AAPL": {
    "last_updated": "2026-03-12T11:51:56.905461Z",
    "last_fetch_status": "success",
    "data_points": 79
  },
  "VGT": {
    "last_updated": "2026-03-12T11:51:58.027978Z",
    "last_fetch_status": "success",
    "data_points": 79
  },
  "QUBT": {
    "last_updated": "2026-03-12T11:51:59.116626Z",
    "last_fetch_status": "success",
    "data_points": 79
  },
  "IONQ": {
    "last_updated": "2026-03-12T11:52:00.183569Z",
    "last_fetch_status": "success",
    "data_points": 79
  },
  "QQQM": {
    "last_updated": "2026-03-12T11:52:01.267018Z",
    "last_fetch_status": "success",
    "data_points": 79
  },
  "MGK": {
    "last_updated": "2026-03-12T11:52:02.390048Z",
    "last_fetch_status": "success",
    "data_points": 79
  },
  "VUG": {
    "last_updated": "2026-03-12T11:52:03.519183Z",
    "last_fetch_status": "success",
    "data_points": 79
  },
  "SPLV": {
    "last_updated": "2026-03-12T11:52:04.737560Z",
    "last_fetch_status": "success",
    "data_points": 79
  },
  "SCHD": {
    "last_updated": "2026-03-12T11:52:05.931423Z",
    "last_fetch_status": "success",
    "data_points": 79
  },
  "DGRO": {
    "last_updated": "2026-03-12T07:08:11.687817Z",
    "last_fetch_status": "success",
    "data_points": 79
  },
  "VIG": {
    "last_updated": "2026-03-12T07:08:12.971834Z",
    "last_fetch_status": "success",
    "data_points": 79
  },
  "VYM": {
    "last_updated": "2026-03-12T07:08:14.264284Z",
    "last_fetch_status": "success",
    "data_points": 79
  },
  "XLE": {
    "last_updated": "2026-03-12T07:08:15.596187Z",
    "last_fetch_status": "success",
    "data_points": 79
  },
  "FENY": {
    "last_updated": "2026-03-12T07:08:16.871032Z",
    "last_fetch_status": "success",
    "data_points": 79
  },
  "VDE": {
    "last_updated": "2026-03-12T08:03:02.013622Z",
    "last_fetch_status": "success",
    "data_points": 79
  },
  "MA": {
    "last_updated": "2026-03-12T08:03:03.159482Z",
    "last_fetch_status": "success",
    "data_points": 79
  },
  "V": {
    "last_updated": "2026-03-12T08:03:04.274273Z",
    "last_fetch_status": "success",
    "data_points": 79
  },
  "JPM": {
    "last_updated": "2026-03-12T08:03:05.448937Z",
    "last_fetch_status": "success",
    "data_points": 79
  },
  "AXON": {
    "last_updated": "2026-03-12T08:03:06.516435Z",
    "last_fetch_status": "success",
    "data_points": 79
  },
  "HWM": {
    "last_updated": "2026-03-12T08:03:12.163496Z",
    "last_fetch_status": "success",
    "data_points": 79
  },
  "EME": {
    "last_updated": "2026-03-12T09:11:00.203861Z",
    "last_fetch_status": "success",
    "data_points": 79
  },
  "TEM": {
    "last_updated": "2026-03-12T09:11:05.953795Z",
    "last_fetch_status": "success",
    "data_points": 79
  },
  "FIX": {
    "last_updated": "2026-03-12T09:11:07.092265Z",
    "last_fetch_status": "success",
    "data_points": 80
  },
  "VGK": {
    "last_updated": "2026-03-12T09:11:08.247445Z",
    "last_fetch_status": "success",
    "data_points": 79
  },
  "GLD": {
    "last_updated": "2026-03-12T09:11:09.334240Z",
    "last_fetch_status": "success",
    "data_points": 79
  },
  "ITA": {
    "last_updated": "2026-03-12T09:11:01.383584Z",
    "last_fetch_status": "success",
    "data_points": 79
  },
  "FSTA": {
    "last_updated": "2026-03-12T09:11:02.498430Z",
    "last_fetch_status": "success",
    "data_points": 79
  },
  "VDC": {
    "last_updated": "2026-03-12T09:11:03.702323Z",
    "last_fetch_status": "success",
    "data_points": 79
  },
  "XLP": {
    "last_updated": "2026-03-12T09:11:04.864922Z",
    "last_fetch_status": "success",
    "data_points": 79
  },
  "VEA": {
    "last_updated": "2026-03-12T08:03:07.625913Z",
    "last_fetch_status": "success",
    "data_points": 76
  },
  "VWO": {
    "last_updated": "2026-03-12T08:03:08.741160Z",
    "last_fetch_status": "success",
    "data_points": 76
  },
  "BND": {
    "last_updated": "2026-03-12T08:03:09.884309Z",
    "last_fetch_status": "success",
    "data_points": 76
  },
  "VTIP": {
    "last_updated": "2026-03-12T08:03:10.991042Z",
    "last_fetch_status": "success",
    "data_points": 76
  }
}