{
  "TEST": {
    "last_updated": "2026-02-14T18:44:42.761347Z",
    "last_fetch_status": "success",
    "data_points": 1
  },
  "NVDA": {
    "last_updated": "2026-02-17T11:48:39.573069Z",
    "last_fetch_status": "success",
    "data_points": 100
  },
  "AMD": {
    "last_updated": "2026-02-17T11:48:40.700354Z",
    "last_fetch_status": "success",
    "data_points": 100
  },
  "INTC": {
    "last_updated": "2026-02-17T11:48:41.899532Z",
    "last_fetch_status": "success",
    "data_points": 100
  },
  "SOXX": {
    "last_updated": "2026-02-17T11:48:43.113221Z",
    "last_fetch_status": "success",
    "data_points": 100
  },
  "MSFT": {
    "last_updated": "2026-02-17T11:48:44.294937Z",
    "last_fetch_status": "success",
    "data_points": 100
  },
  "GOOGL": {
    "last_updated": "2026-02-17T11:48:45.438550Z",
    "last_fetch_status": "success",
    "data_points": 100
  },
  "AMZN": {
    "last_updated": "2026-02-17T10:58:13.546684Z",
    "last_fetch_status": "success",
    "data_points": 100
  },
  "META": {
    "last_updated": "2026-02-17T10:58:15.724020Z",
    "last_fetch_status": "success",
    "data_points": 100
  },
  "SPY": {
    "last_updated": "2026-02-17T10:58:16.888929Z",
    "last_fetch_status": "success",
    "data_points": 100
  },
  "QQQ": {
    "last_updated": "2026-02-17T10:58:18.017516Z",
    "last_fetch_status": "success",
    "data_points": 100
  },
  "VIX": {
    "last_updated": "2026-02-14T20:35:29.964419Z",
    "last_fetch_status": "failed: API Error: Invalid API call. Please retry or visit the documentation (https://www.alphavantage.co/documentation/) for TIME_SERIES_DAILY.",
    "data_points": 0
  },
  "BTC-USD": {
    "last_updated": "2026-02-17T10:58:11.331185Z",
    "last_fetch_status": "success",
    "data_points": 95
  },
  "ETH-USD": {
    "last_updated": "2026-02-17T10:58:10.246522Z",
    "last_fetch_status": "success",
    "data_points": 95
  },
  "^VIX": {
    "last_updated": "2026-02-17T10:58:14.630648Z",
    "last_fetch_status": "success",
    "data_points": 64
  },
  "NQ=F": {
    "last_updated": "2026-02-17T11:48:46.566111Z",
    "last_fetch_status": "success",
    "data_points": 65
  },
  "AVGO": {
    "last_updated": "2026-02-17T10:58:12.460972Z",
    "last_fetch_status": "success",
    "data_points": 62
  },
  "ASML": {
    "last_updated": "2026-02-17T11:48:47.744408Z",
    "last_fetch_status": "success",
    "data_points": 62
  },
  "LRCX": {
    "last_updated": "2026-02-17T11:48:48.901398Z",
    "last_fetch_status": "success",
    "data_points": 62
  },
  "MU": {
    "last_updated": "2026-02-17T11:48:50.121557Z",
    "last_fetch_status": "success",
    "data_points": 62
  },
  "TSM": {
    "last_updated": "2026-02-17T13:18:40.455803Z",
    "last_fetch_status": "success",
    "data_points": 62
  },
  "PLTR": {
    "last_updated": "2026-02-17T13:18:41.571733Z",
    "last_fetch_status": "success",
    "data_points": 62
  },
  "CRWD": {
    "last_updated": "2026-02-17T13:18:42.663683Z",
    "last_fetch_status": "success",
    "data_points": 62
  },
  "NFLX": {
    "last_updated": "2026-02-17T13:18:43.900551Z",
    "last_fetch_status": "success",
    "data_points": 62
  },
  "AAPL": {
    "last_updated": "2026-02-17T13:18:45.040693Z",
    "last_fetch_status": "success",
    "data_points": 62
  },
  "VGT": {
    "last_updated": "2026-02-17T13:18:46.157488Z",
    "last_fetch_status": "success",
    "data_points": 62
  },
  "QUBT": {
    "last_updated": "2026-02-17T13:18:47.221158Z",
    "last_fetch_status": "success",
    "data_points": 62
  },
  "IONQ": {
    "last_updated": "2026-02-17T13:18:48.384173Z",
    "last_fetch_status": "success",
    "data_points": 62
  },
  "QQQM": {
    "last_updated": "2026-02-17T13:18:49.599880Z",
    "last_fetch_status": "success",
    "data_points": 62
  },
  "MGK": {
    "last_updated": "2026-02-17T13:18:50.815766Z",
    "last_fetch_status": "success",
    "data_points": 62
  },
  "VUG": {
    "last_updated": "2026-02-17T14:29:37.174670Z",
    "last_fetch_status": "success",
    "data_points": 62
  },
  "SPLV": {
    "last_updated": "2026-02-17T14:29:38.383839Z",
    "last_fetch_status": "success",
    "data_points": 62
  },
  "SCHD": {
    "last_updated": "2026-02-17T14:29:39.494306Z",
    "last_fetch_status": "success",
    "data_points": 62
  },
  "DGRO": {
    "last_updated": "2026-02-17T14:29:40.726142Z",
    "last_fetch_status": "success",
    "data_points": 62
  },
  "VIG": {
    "last_updated": "2026-02-17T14:29:41.873902Z",
    "last_fetch_status": "success",
    "data_points": 62
  },
  "VYM": {
    "last_updated": "2026-02-17T14:29:43.016412Z",
    "last_fetch_status": "success",
    "data_points": 62
  },
  "XLE": {
    "last_updated": "2026-02-17T14:29:44.287882Z",
    "last_fetch_status": "success",
    "data_points": 62
  },
  "FENY": {
    "last_updated": "2026-02-17T14:29:45.444861Z",
    "last_fetch_status": "success",
    "data_points": 62
  },
  "VDE": {
    "last_updated": "2026-02-17T14:29:46.677114Z",
    "last_fetch_status": "success",
    "data_points": 62
  },
  "MA": {
    "last_updated": "2026-02-17T14:29:47.885889Z",
    "last_fetch_status": "success",
    "data_points": 62
  },
  "V": {
    "last_updated": "2026-02-17T15:29:56.040348Z",
    "last_fetch_status": "success",
    "data_points": 63
  },
  "JPM": {
    "last_updated": "2026-02-17T15:29:57.328112Z",
    "last_fetch_status": "success",
    "data_points": 63
  },
  "AXON": {
    "last_updated": "2026-02-17T15:29:58.512318Z",
    "last_fetch_status": "success",
    "data_points": 63
  },
  "HWM": {
    "last_updated": "2026-02-17T15:29:59.790739Z",
    "last_fetch_status": "success",
    "data_points": 63
  },
  "EME": {
    "last_updated": "2026-02-17T15:30:01.049298Z",
    "last_fetch_status": "success",
    "data_points": 63
  },
  "TEM": {
    "last_updated": "2026-02-17T15:30:07.286420Z",
    "last_fetch_status": "success",
    "data_points": 63
  },
  "FIX": {
    "last_updated": "2026-02-17T09:58:26.746498Z",
    "last_fetch_status": "success",
    "data_points": 63
  },
  "VGK": {
    "last_updated": "2026-02-17T10:58:08.070131Z",
    "last_fetch_status": "success",
    "data_points": 62
  },
  "GLD": {
    "last_updated": "2026-02-17T10:58:09.155354Z",
    "last_fetch_status": "success",
    "data_points": 62
  },
  "ITA": {
    "last_updated": "2026-02-17T15:30:02.346538Z",
    "last_fetch_status": "success",
    "data_points": 63
  },
  "FSTA": {
    "last_updated": "2026-02-17T15:30:03.534404Z",
    "last_fetch_status": "success",
    "data_points": 63
  },
  "VDC": {
    "last_updated": "2026-02-17T15:30:04.767378Z",
    "last_fetch_status": "success",
    "data_points": 63
  },
  "XLP": {
    "last_updated": "2026-02-17T15:30:06.083006Z",
    "last_fetch_status": "success",
    "data_points": 63
  }
}